colvert/__init__.py
colvert/__main__.py
colvert/_version.py
colvert/ai.py
colvert/demo.py
colvert/settings.py
colvert/cli/__init__.py
colvert/cli/ai.py
colvert/cli/config.py
colvert/cli/daemon.py
colvert/cli/sample.py
colvert/database/__init__.py
colvert/database/database.py
colvert/database/error.py
colvert/database/query.py
colvert/database/result.py
colvert/docs/configuration.md
colvert/docs/getting-started.md
colvert/docs/import-export.md
colvert/docs/index.md
colvert/docs/samples.md
colvert/docs/ai/index.md
colvert/docs/ai/prompt.png
colvert/docs/charts/index.md
colvert/docs/charts/line/index.md
colvert/docs/charts/line/line.png
colvert/docs/charts/pie/hole.png
colvert/docs/charts/pie/index.md
colvert/docs/charts/pie/pie.png
colvert/docs/charts/scatter_map/color.png
colvert/docs/charts/scatter_map/index.md
colvert/docs/charts/scatter_map/map_style.png
colvert/docs/charts/scatter_map/scatter_map.png
colvert/docs/charts/scatter_map/size.png
colvert/docs/charts/table/index.md
colvert/docs/charts/table/table.png
colvert/tests/__init__.py
colvert/tests/conftest.py
colvert/tests/test_ai.py
colvert/tests/test_settings.py
colvert/tests/database/test_database.py
colvert/tests/database/test_query.py
colvert/tests/ui/__init__.py
colvert/tests/ui/conftest.py
colvert/tests/ui/charts/__init__.py
colvert/tests/ui/charts/test_charts.py
colvert/tests/ui/charts/test_line.py
colvert/tests/ui/charts/test_pie.py
colvert/tests/ui/charts/test_scatter_map.py
colvert/tests/ui/charts/test_types.py
colvert/tests/ui/routes/test_completion.py
colvert/tests/ui/routes/test_components.py
colvert/tests/ui/routes/test_docs.py
colvert/tests/ui/routes/test_index.py
colvert/tests/ui/routes/test_query_form.py
colvert/tests/ui/routes/test_results.py
colvert/ui/__init__.py
colvert/ui/components.py
colvert/ui/helpers.py
colvert/ui/charts/__init__.py
colvert/ui/charts/base.py
colvert/ui/charts/line.py
colvert/ui/charts/pie.py
colvert/ui/charts/scatter_map.py
colvert/ui/charts/table.py
colvert-0.3.0.dist-info/METADATA
colvert-0.3.0.dist-info/WHEEL
colvert-0.3.0.dist-info/entry_points.txt
colvert-0.3.0.dist-info/licenses/LICENSE.txt
colvert-0.3.0.dist-info/RECORD
