Metadata-Version: 2.4
Name: colvert
Version: 0.3.0
Summary: colvert is a Frontend for DuckDB a fast and lightweight in-memory database designed for analytical queries. It's design to be a simple and easy to use tool for data analysis and visualization.
Project-URL: Documentation, https://github.com/julien-duponchelle/colvert#readme
Project-URL: Issues, https://github.com/julien-duponchelle/colvert/issues
Project-URL: Source, https://github.com/julien-duponchelle/colvert
Author-email: Julien Duponchelle <julien@duponchelle.info>
License-Expression: Apache-2.0
License-File: LICENSE.txt
Classifier: Development Status :: 3 - Alpha
Classifier: Environment :: Web Environment
Classifier: Framework :: AsyncIO
Classifier: Intended Audience :: End Users/Desktop
Classifier: Intended Audience :: Science/Research
Classifier: License :: OSI Approved :: Apache Software License
Classifier: Programming Language :: Python
Classifier: Programming Language :: Python :: 3.11
Classifier: Programming Language :: Python :: 3.12
Classifier: Programming Language :: Python :: Implementation :: CPython
Classifier: Topic :: Scientific/Engineering :: Visualization
Requires-Python: >=3.11
Requires-Dist: aiohttp-jinja2>=1.5.1
Requires-Dist: aiohttp>=3.8.5
Requires-Dist: click>=8.1.7
Requires-Dist: colorama>=0.4.6
Requires-Dist: duckdb>=1.1.3
Requires-Dist: litellm>=1.53.7
Requires-Dist: markdown
Requires-Dist: pandas>=2.2.1
Requires-Dist: platformdirs>=4.3.6
Requires-Dist: plotly>=5.20.0
Requires-Dist: rocher>=0.44.0
Requires-Dist: toml>=0.10.2
